pywsl/__init__.py
pywsl/cpe/__init__.py
pywsl/cpe/cpe_ene.py
pywsl/pul/__init__.py
pywsl/pul/pu_mr.py
pywsl/pul/pumil_mr.py
pywsl/pul/chainer/__init__.py
pywsl/pul/chainer/functions/__init__.py
pywsl/pul/chainer/functions/nnpu_risk.py
pywsl/pul/chainer/functions/pu_accuracy.py
pywsl/ssl/__init__.py
pywsl/ssl/pnu_mr.py
pywsl/utils/__init__.py
pywsl/utils/check.py
pywsl/utils/comcalc.py
pywsl/utils/datasets.py
pywsl/utils/models.py
pywsl/utils/syndata.py
pywsl/utils/timer.py
pywsl/utils/tools4chainer.py
tests/cpe_tests/__init__.py
tests/cpe_tests/test_cpe_ene.py
tests/pul_tests/__init__.py
tests/pul_tests/test_pu_mr.py
tests/pul_tests/test_pumil_mr.py
tests/pul_tests/chainer_tests/__init__.py
tests/pul_tests/chainer_tests/functions_tests/__init__.py
tests/pul_tests/chainer_tests/functions_tests/test_nnpu_risk.py
tests/pul_tests/chainer_tests/functions_tests/test_pu_accuracy.py
tests/ssl_tests/__init__.py
tests/ssl_tests/test_pnu_mr.py
pywsl-0.1.4.dist-info/LICENSE
pywsl-0.1.4.dist-info/METADATA
pywsl-0.1.4.dist-info/WHEEL
pywsl-0.1.4.dist-info/top_level.txt
pywsl-0.1.4.dist-info/RECORD
