Metadata-Version: 2.1
Name: pywsl
Version: 0.1.4
Summary: Code for weakly supervised learning
Home-page: https://github.com/t-sakai-kure/pywsl
Author: Tomoya Sakai
Author-email: t.sakai.kure@gmail.com
License: MIT
Platform: UNKNOWN
Classifier: Intended Audience :: Developers
Classifier: Intended Audience :: Education
Classifier: Intended Audience :: Science/Research
Classifier: License :: OSI Approved :: MIT License
Classifier: Programming Language :: Python :: 3.4
Classifier: Topic :: Software Development :: Libraries :: Python Modules
